anydb/__init__.py
anydb/__main__.py
anydb/config.yml
anydb/logger.yml
anydb/controllers/__init__.py
anydb/controllers/base.py
anydb/controllers/mongo.py
anydb/controllers/nuke.py
anydb/services/__init__.py
anydb/services/data.py
anydb/services/docker.py
anydb/services/util.py
anydb-0.3.3.dist-info/METADATA
anydb-0.3.3.dist-info/RECORD
anydb-0.3.3.dist-info/WHEEL
anydb-0.3.3.dist-info/entry_points.txt
anydb-0.3.3.dist-info/top_level.txt
