Metadata-Version: 2.1
Name: anydb
Version: 0.3.3
Summary: Manage dotfiles with stow
Home-page: https://github.com/codejamninja/anydb
Author: Jam Risser
Author-email: jam@codejam.ninja
License: MIT
Keywords: ubuntu remaster fork install linux
Platform: UNKNOWN
Classifier: Development Status :: 4 - Beta
Classifier: Intended Audience :: Developers
Classifier: Topic :: Utilities
Classifier: License :: OSI Approved :: MIT License
Classifier: Programming Language :: Python :: 2
Classifier: Programming Language :: Python :: 2.7
Classifier: Programming Language :: Python :: 3
Classifier: Programming Language :: Python :: 3.3
Classifier: Programming Language :: Python :: 3.4
Classifier: Programming Language :: Python :: 3.5
Requires-Dist: backports.shutil-get-terminal-size (==1.0.0)
Requires-Dist: blessings (==1.7)
Requires-Dist: cement (==2.10.12)
Requires-Dist: certifi (==2018.4.16)
Requires-Dist: cfoundation (==0.3.1)
Requires-Dist: chardet (==3.0.4)
Requires-Dist: colorama (==0.3.9)
Requires-Dist: cursor (==1.2.0)
Requires-Dist: docker (==3.5.0)
Requires-Dist: docker-pycreds (==0.3.0)
Requires-Dist: enum34 (==1.1.6)
Requires-Dist: halo (==0.0.12)
Requires-Dist: idna (==2.7)
Requires-Dist: inquirer (==2.4.0)
Requires-Dist: log-symbols (==0.0.11)
Requires-Dist: munch (==2.3.2)
Requires-Dist: pydash (==4.5.0)
Requires-Dist: PyYAML (==3.12)
Requires-Dist: readchar (==2.0.1)
Requires-Dist: requests (==2.19.1)
Requires-Dist: sarge (==0.1.5.post0)
Requires-Dist: six (==1.11.0)
Requires-Dist: spinners (==0.0.19)
Requires-Dist: termcolor (==1.1.0)
Requires-Dist: urllib3 (==1.23)
Requires-Dist: websocket-client (==0.48.0)
